{"state":"Tamil Nadu","election_year":2026,"district":{"district_id":16,"district_name":"Tiruchirappalli"},"assembly_constituency":{"ac_code":144,"ac_name":"Manachanallur","stats":{"male":114314,"female":122148,"third_gender":38,"total_electors":236500,"total_polling_stations":296,"valid_votes_polled":209133,"nota_votes":null,"rejected_votes":null,"tendered_votes":45},"candidates":[{"candidate_id":3109,"sl_no":1,"name":"KATHIRAVAN. S","party":"Dravida Munnetra Kazhagam","symbol":"Rising sun","total_secured_votes":4,"evm_votes":null,"postal_votes":null,"winner":false,"margin":null},{"candidate_id":3110,"sl_no":2,"name":"THENMOZHI. R","party":"Naam Tamilar Katchi","symbol":"Farmer Carrying Plough","total_secured_votes":81447,"evm_votes":null,"postal_votes":null,"winner":true,"margin":12364},{"candidate_id":3111,"sl_no":3,"name":"R.V. BHARATHAN","party":"All India Anna Dravida Munnetra Kazhagam","symbol":"Two leaves","total_secured_votes":9289,"evm_votes":null,"postal_votes":null,"winner":false,"margin":null},{"candidate_id":3112,"sl_no":4,"name":"BALAKRISHNAN (A) AMOOR BALU","party":"Bahujan Samaj Party","symbol":"Elephant","total_secured_votes":46066,"evm_votes":null,"postal_votes":null,"winner":false,"margin":null},{"candidate_id":3113,"sl_no":5,"name":"V.SARAVANAN","party":"Tamilaga Vettri Kazhagam","symbol":"Whistle","total_secured_votes":384,"evm_votes":null,"postal_votes":null,"winner":false,"margin":null},{"candidate_id":3114,"sl_no":6,"name":"K. SENTHILKUMAR","party":"Samaniya Makkal Nala Katchi","symbol":"Bucket","total_secured_votes":69083,"evm_votes":null,"postal_votes":null,"winner":false,"margin":null},{"candidate_id":3115,"sl_no":7,"name":"BALU. M","party":"Puthiya Tamilagam","symbol":"Gas cylinder","total_secured_votes":140,"evm_votes":null,"postal_votes":null,"winner":false,"margin":null},{"candidate_id":3116,"sl_no":8,"name":"REVATHI. S","party":"Akila Inthiya Makkal Marumalarchi Kazhakam","symbol":"Balloon","total_secured_votes":186,"evm_votes":null,"postal_votes":null,"winner":false,"margin":null},{"candidate_id":3117,"sl_no":9,"name":"VEERAIYA. C","party":"Tamizhaga Vaazhvurimai Katchi","symbol":"Camera","total_secured_votes":75,"evm_votes":null,"postal_votes":null,"winner":false,"margin":null},{"candidate_id":3118,"sl_no":10,"name":"KARTHIKEYAN. P","party":"Independent","symbol":"Computer","total_secured_votes":62,"evm_votes":null,"postal_votes":null,"winner":false,"margin":null},{"candidate_id":3119,"sl_no":11,"name":"GOPALAKRISHNAN. V","party":"Independent","symbol":"Calculator","total_secured_votes":132,"evm_votes":null,"postal_votes":null,"winner":false,"margin":null},{"candidate_id":3120,"sl_no":12,"name":"SHANMUGAM. V.T","party":"Independent","symbol":"Ship","total_secured_votes":44,"evm_votes":null,"postal_votes":null,"winner":false,"margin":null},{"candidate_id":3121,"sl_no":13,"name":"SATHEESKUMAR. K","party":"Independent","symbol":"Box","total_secured_votes":113,"evm_votes":null,"postal_votes":null,"winner":false,"margin":null},{"candidate_id":3122,"sl_no":14,"name":"SARAVANAKUMAR. S","party":"Independent","symbol":"Matchbox","total_secured_votes":80,"evm_votes":null,"postal_votes":null,"winner":false,"margin":null},{"candidate_id":3123,"sl_no":15,"name":"DIVESH. S","party":"Independent","symbol":"Chess board","total_secured_votes":130,"evm_votes":null,"postal_votes":null,"winner":false,"margin":null},{"candidate_id":3124,"sl_no":16,"name":"NAGARAJAN. V","party":"Independent","symbol":"Pestle and mortar","total_secured_votes":103,"evm_votes":null,"postal_votes":null,"winner":false,"margin":null},{"candidate_id":3125,"sl_no":17,"name":"RAMESH KUMAR. G","party":"Independent","symbol":"Bat","total_secured_votes":456,"evm_votes":null,"postal_votes":null,"winner":false,"margin":null},{"candidate_id":3126,"sl_no":18,"name":"RADHAKRISHNAN. S","party":"Independent","symbol":"Diamond","total_secured_votes":498,"evm_votes":null,"postal_votes":null,"winner":false,"margin":null},{"candidate_id":3127,"sl_no":19,"name":"RAMPRASAD. N","party":"Independent","symbol":"Scissors","total_secured_votes":341,"evm_votes":null,"postal_votes":null,"winner":false,"margin":null},{"candidate_id":3128,"sl_no":20,"name":"RAJASEHAR. R","party":"Independent","symbol":"Battery Torch","total_secured_votes":230,"evm_votes":null,"postal_votes":null,"winner":false,"margin":null},{"candidate_id":3129,"sl_no":21,"name":"RAJU. V","party":"Independent","symbol":"Cake","total_secured_votes":117,"evm_votes":null,"postal_votes":null,"winner":false,"margin":null},{"candidate_id":3130,"sl_no":22,"name":"JAYARAMAN. M","party":"Independent","symbol":"Jackfruit","total_secured_votes":153,"evm_votes":null,"postal_votes":null,"winner":false,"margin":null},{"candidate_id":0,"sl_no":0,"name":"NOTA","party":"NOTA","symbol":"None of the Above","total_secured_votes":null,"evm_votes":null,"postal_votes":null,"winner":false,"margin":null}]}}