{"state":"Tamil Nadu","election_year":2026,"district":{"district_id":18,"district_name":"Cuddalore"},"assembly_constituency":{"ac_code":152,"ac_name":"Vriddhachalam","stats":{"male":119650,"female":121111,"third_gender":22,"total_electors":240783,"total_polling_stations":317,"valid_votes_polled":208431,"nota_votes":755,"rejected_votes":0,"tendered_votes":1},"candidates":[{"candidate_id":845,"sl_no":1,"name":"ANANTHI DHANDAPANI","party":"Naam Tamilar Katchi","symbol":"Farmer Carrying Plough","total_secured_votes":6047,"evm_votes":null,"postal_votes":null,"winner":false,"margin":null},{"candidate_id":846,"sl_no":2,"name":"SIVAPRAKASAM.V","party":"Bahujan Samaj Party","symbol":"Elephant","total_secured_votes":374,"evm_votes":null,"postal_votes":null,"winner":false,"margin":null},{"candidate_id":847,"sl_no":3,"name":"PREMALLATHA VIJAYAKANT","party":"Desiya Murpokku Dravida Kazhagam","symbol":"Nagara","total_secured_votes":69351,"evm_votes":null,"postal_votes":null,"winner":true,"margin":2387},{"candidate_id":848,"sl_no":4,"name":"ARIVAZHAGAN.E.N","party":"Tamizhaga Vaazhvurimai Katchi","symbol":"Camera","total_secured_votes":1896,"evm_votes":null,"postal_votes":null,"winner":false,"margin":null},{"candidate_id":849,"sl_no":5,"name":"ARIVUDAINAMBI.S","party":"Anti Corruption Dynamic Party","symbol":"Jackfruit","total_secured_votes":904,"evm_votes":null,"postal_votes":null,"winner":false,"margin":null},{"candidate_id":850,"sl_no":6,"name":"SATHIYA.B","party":"Anna Makkal Katchi","symbol":"Coconut farm","total_secured_votes":160,"evm_votes":null,"postal_votes":null,"winner":false,"margin":null},{"candidate_id":851,"sl_no":7,"name":"SIDHARTHAN.S","party":"Desiya Makkal Sakthi Katchi","symbol":"Football player","total_secured_votes":225,"evm_votes":null,"postal_votes":null,"winner":false,"margin":null},{"candidate_id":852,"sl_no":8,"name":"GNANASUNDARI.M","party":"Aanaithinthiya Jananayaka Pathukappu Kazhagam","symbol":"Gas cylinder","total_secured_votes":611,"evm_votes":null,"postal_votes":null,"winner":false,"margin":null},{"candidate_id":853,"sl_no":9,"name":"DR.TAMIZHARASI.P","party":"Pattali Makkal Katchi","symbol":"Mango","total_secured_votes":59791,"evm_votes":null,"postal_votes":null,"winner":false,"margin":null},{"candidate_id":854,"sl_no":10,"name":"VIJAY.S","party":"Tamilaga Vettri Kazhagam","symbol":"Whistle","total_secured_votes":66964,"evm_votes":null,"postal_votes":null,"winner":false,"margin":null},{"candidate_id":855,"sl_no":11,"name":"EZHILKUMAR.K","party":"Independent","symbol":"Bat","total_secured_votes":175,"evm_votes":null,"postal_votes":null,"winner":false,"margin":null},{"candidate_id":856,"sl_no":12,"name":"SIVASANKARAN.K","party":"Independent","symbol":"Capsicum","total_secured_votes":161,"evm_votes":null,"postal_votes":null,"winner":false,"margin":null},{"candidate_id":857,"sl_no":13,"name":"SRINIVASAN.R","party":"Independent","symbol":"Gift pack","total_secured_votes":328,"evm_votes":null,"postal_votes":null,"winner":false,"margin":null},{"candidate_id":858,"sl_no":14,"name":"DURAI.K","party":"Independent","symbol":"Mike","total_secured_votes":738,"evm_votes":null,"postal_votes":null,"winner":false,"margin":null},{"candidate_id":859,"sl_no":15,"name":"DEIVEEGADASS.M","party":"Independent","symbol":"Air conditioner","total_secured_votes":163,"evm_votes":null,"postal_votes":null,"winner":false,"margin":null},{"candidate_id":860,"sl_no":16,"name":"BALU.P","party":"Independent","symbol":"Almirah","total_secured_votes":252,"evm_votes":null,"postal_votes":null,"winner":false,"margin":null},{"candidate_id":861,"sl_no":17,"name":"PRABAKARAN.T","party":"Independent","symbol":"Ship","total_secured_votes":129,"evm_votes":null,"postal_votes":null,"winner":false,"margin":null},{"candidate_id":862,"sl_no":18,"name":"JAYAPRAKASH.S","party":"Independent","symbol":"Diamond","total_secured_votes":162,"evm_votes":null,"postal_votes":null,"winner":false,"margin":null},{"candidate_id":0,"sl_no":0,"name":"NOTA","party":"NOTA","symbol":"None of the Above","total_secured_votes":755,"evm_votes":null,"postal_votes":null,"winner":false,"margin":null}]}}